fanvue_mcp/__init__.py
fanvue_mcp/config.py
fanvue_mcp/server.py
fanvue_mcp-0.1.1.dist-info/METADATA
fanvue_mcp-0.1.1.dist-info/WHEEL
fanvue_mcp-0.1.1.dist-info/entry_points.txt
fanvue_mcp-0.1.1.dist-info/RECORD
