Metadata-Version: 2.4
Name: fanvue-mcp
Version: 0.1.1
Summary: Fanvue MCP Server
Requires-Python: >=3.11
Requires-Dist: fastmcp>=2.13.0.2
Requires-Dist: httpx>=0.28.1
Requires-Dist: uvicorn>=0.38.0
